ryomath_demo/init.py
ryomath_demo/multiply.py
ryomath_demo-0.1.0.dist-info/METADATA
ryomath_demo-0.1.0.dist-info/WHEEL
ryomath_demo-0.1.0.dist-info/top_level.txt
ryomath_demo-0.1.0.dist-info/RECORD
