Metadata-Version: 2.4
Name: ryomath_demo
Version: 0.1.0
Summary: Demo package for PyPI publish
Author-email: Your Name <your.email@example.com>
License: MIT
Requires-Python: >=3.6
